roboidlab/__init__.py
roboidlab/grid.py
roboidlab/keyevent.py
roboidlab/line_recorder.py
roboidlab/q_game.py
roboidlab-1.0.3.dist-info/LICENSE
roboidlab-1.0.3.dist-info/METADATA
roboidlab-1.0.3.dist-info/WHEEL
roboidlab-1.0.3.dist-info/top_level.txt
roboidlab-1.0.3.dist-info/RECORD
