Metadata-Version: 2.1
Name: roboidlab
Version: 1.0.3
Summary: Python Package for Roboid Laboratory
Home-page: UNKNOWN
Author: Kwang-Hyun Park
Author-email: akaii@kw.ac.kr
License: UNKNOWN
Platform: UNKNOWN
Classifier: License :: OSI Approved :: GNU Lesser General Public License v2 or later (LGPLv2+)
Requires-Python: >=3
Requires-Dist: roboid
Requires-Dist: pynput
Requires-Dist: pandas
Requires-Dist: matplotlib
